{"version":"0.1.20260311","status_code":20000,"status_message":"Ok.","time":"6.7566 sec.","cost":0.004,"tasks_count":1,"tasks_error":0,"tasks":[{"id":"03161257-4353-0139-0000-f13017828fb5","status_code":20000,"status_message":"Ok.","time":"6.5844 sec.","cost":0.004,"result_count":1,"path":["v3","serp","google","ai_mode","live","advanced"],"data":{"api":"serp","function":"live","se":"google","se_type":"ai_mode","keyword":"lions mane salt scrub for face and body","language_code":"en","location_code":2840,"device":"desktop","os":"windows"},"result":[{"keyword":"lions mane salt scrub for face and body","type":"ai_mode","se_domain":"google.com","location_code":2840,"language_code":"en","check_url":"https://www.google.com/search?q=lions%20mane%20salt%20scrub%20for%20face%20and%20body\u0026hl=en\u0026gl=US\u0026udm=50\u0026uule=w\u002BCAIQIFISCQs2MuSEtepUEUK33kOSuTsc","datetime":"2026-03-16 10:57:36 \u002B00:00","spell":null,"refinement_chips":null,"item_types":["ai_overview"],"se_results_count":0,"items_count":1,"items":[{"type":"ai_overview","rank_group":1,"rank_absolute":1,"page":1,"position":"left","xpath":"/html[1]/body[1]/div[2]/div[1]/div[9]/div[1]/div[2]/div[1]/section[1]/div[1]/div[1]/div[3]/div[6]/div[1]/div[1]/div[1]/div[3]","markdown":"Lion\u0027s mane salt scrubs are designed to exfoliate and nourish the skin by combining mineral-rich salts with the antioxidant and anti-inflammatory benefits of **Lion\u0027s Mane mushroom extract** . These scrubs are primarily used to improve skin texture, support collagen production, and provide deep hydration.[[1]](https://www.saltability.com/products/himalayan-salt-lions-mane-scrub-8-oz?srsltid=AfmBOopE2O0bHE_871-01kdbqIzK25yA2ql5bS_p76j5zBzgE0d1tR_6#:~:text=$24.00%20USD,per%20week%20for%20best%20results.)[[2]](https://www.google.com/search?q=product\u0026prds=pvt:hg,productid:6627771179973779464,catalogid:8916746914933518999,gpcid:10023773780186035872\u0026ibp=oshop)[[3]](https://moonandskin.com/blogs/glow-up/discovering-the-lions-mane-mushroom-benefits-for-skin-natures-hidden-gem?srsltid=AfmBOoqvjhD1TuIZ5st90HEseVct4URyfCmZwyj7k35j9odeJPLJv-YT#:~:text=By%20incorporating%20lion\u0027s%20mane%20into%20our%20skincare%20regimen%2C%20we%20can,the%20effects%20of%20sun%20exposure.)[[4]](https://skintherapy.com/from-the-forest-to-your-face-how-mushrooms-are-revolutionizing-skincare/#:~:text=Lion\u0027s%20Mane:%20This%20mushroom%20contains,to%20help%20support%20healthy%20skin.)\n\nBenefits for Face and Body\n\n- **Exfoliation and Renewal** : Mineral-rich Sea, Himalayan, or Dead Sea salts gently polish away dead skin cells to reveal smoother, more radiant skin underneath.\n- **Anti-Aging Support** : Lion\u0027s Mane mushroom contains polysaccharides and antioxidants that may boost **collagen and elasticity** , helping to reduce the appearance of fine lines.\n- **Soothing Inflammation** : Its anti-inflammatory properties can help reduce redness, calm irritation, and support natural skin healing.\n- **Hydration** : Formulations often include nourishing oils like **sweet almond and jojoba oil** , which lock in moisture and leave the skin feeling soft.[[1]](https://www.saltability.com/products/himalayan-salt-lions-mane-scrub-8-oz?srsltid=AfmBOopE2O0bHE_871-01kdbqIzK25yA2ql5bS_p76j5zBzgE0d1tR_6#:~:text=$24.00%20USD,per%20week%20for%20best%20results.)[[2]](https://www.google.com/search?q=product\u0026prds=pvt:hg,productid:6627771179973779464,catalogid:8916746914933518999,gpcid:10023773780186035872\u0026ibp=oshop)[[3]](https://www.instagram.com/p/DVMTWhEDlSg/#:~:text=%E2%9C%A8%20BUY%204%2C%20GET%202,saltability)[[4]](https://eatfungies.com/blogs/news/perfect-your-skincare-routine-with-lion-s-mane?srsltid=AfmBOorDwjG0ATx5bAHrjak0vmm5O2XXeOEENFyGHgbpsxNgt9xVJJ2D#:~:text=Cheat%20Sheet,fight%20inflammation%20before%20it%20starts.)[[5]](https://skintherapy.com/from-the-forest-to-your-face-how-mushrooms-are-revolutionizing-skincare/#:~:text=Lion\u0027s%20Mane:%20This%20mushroom%20contains,to%20help%20support%20healthy%20skin.)[[6]](https://moonandskin.com/blogs/glow-up/discovering-the-lions-mane-mushroom-benefits-for-skin-natures-hidden-gem?srsltid=AfmBOoqvjhD1TuIZ5st90HEseVct4URyfCmZwyj7k35j9odeJPLJv-YT#:~:text=By%20incorporating%20lion\u0027s%20mane%20into%20our%20skincare%20regimen%2C%20we%20can,the%20effects%20of%20sun%20exposure.)\n\nRecommended Products\n\nThe following products incorporate Lion\u0027s Mane mushroom into exfoliating salt-based formulas:[[1]](https://www.midwestseasaltcompany.com/exfoliating-lions-main-mushroom-scrub-128oz/)\n\n[![Himalayan Salt Lion\u0026#39;s Mane Scrub](https://api.dataforseo.com/cdn/i/03161257-4353-0139-0000-f13017828fb5:4)\nHimalayan Salt Lion\u0027s Mane Scrub $24.00 Saltability](https://www.google.com/search?ibp=oshop\u0026prds=pvt:hg,pvo:29,imageDocid:14355365782867049316,gpcid:10023773780186035872,headlineOfferDocid:4724190994376421910,catalogid:8916746914933518999,productDocid:6627771179973779464\u0026q=product\u0026sa=X\u0026ved=2ahUKEwiiucGuoaSTAxX4mGoFHehCGZMQgLcPegQICBAC) Ask about\n\n- **Features** : Formulated with Sea Salt, Himalayan Salt, and Lion\u2019s Mane extract.\n- **Additional Ingredients** : Contains a blend of sweet almond oil, jojoba oil, oat extract, arnica, and Vitamin E.\n- **Usage** : Recommended to mix with a small amount of water to create a paste and massage onto damp skin 2\u20133 times per week.\n- Available at [Saltability](https://www.saltability.com/products/himalayan-salt-lions-mane-scrub-8-oz).\n\n[![Exfoliating Lions Main Mushroom Scrub](https://api.dataforseo.com/cdn/i/03161257-4353-0139-0000-f13017828fb5:5)\nExfoliating Lions Main Mushroom Scrub $57.03 Walmart - The Midwest Sea Salt Company \u0026 more](https://www.google.com/search?ibp=oshop\u0026prds=pvt:hg,pvo:29,mid:576462878899398168,imageDocid:6383926006675907478,headlineOfferDocid:15373118500153604702,catalogid:4621011338833908465,productDocid:298150119403178508\u0026q=product\u0026sa=X\u0026ved=2ahUKEwiiucGuoaSTAxX4mGoFHehCGZMQgLcPegQICBAQ) Ask about\n\n- **Features** : A Dead Sea Salt-based scrub designed to balance and refresh skin.\n- **Scents** : Available in various scents including **Lemongrass**, **Peppermint** , and **Lavender** , as well as an unscented version.\n- **Size** : Offered in a large 128 oz (1 gallon) tub suitable for heavy users or professional settings.\n- Available at [The Midwest Sea Salt Company](https://www.midwestseasaltcompany.com/exfoliating-lions-main-mushroom-scrub-128oz/) and Walmart.[[1]](https://www.midwestseasaltcompany.com/exfoliating-lions-main-mushroom-scrub-128oz/#:~:text=Product%20Description,Choose%20Options)[[2]](https://www.google.com/search?q=product\u0026prds=pvt:hg,productid:6627771179973779464,catalogid:8916746914933518999,gpcid:10023773780186035872\u0026ibp=oshop)[[3]](https://www.saltability.com/products/himalayan-salt-lions-mane-scrub-8-oz?srsltid=AfmBOopE2O0bHE_871-01kdbqIzK25yA2ql5bS_p76j5zBzgE0d1tR_6#:~:text=$24.00%20USD,per%20week%20for%20best%20results.)[[4]](https://www.google.com/search?q=product\u0026prds=pvt:hg,productid:298150119403178508,catalogid:4621011338833908465,mid:576462878899398168\u0026ibp=oshop)[[5]](https://www.google.com/search?q=product\u0026prds=pvt:hg,productid:7297618303635761298,catalogid:9786592570481028313\u0026ibp=oshop)[[6]](https://www.google.com/search?q=product\u0026prds=pvt:hg,productid:11995534751749398251,catalogid:7286353642936147147,gpcid:4756473384681669255,mid:576462878899398168\u0026ibp=oshop)[[7]](https://www.google.com/search?q=product\u0026prds=pvt:hg,productid:8000089833852050309,catalogid:8960174552859667425\u0026ibp=oshop)\n\nSafety and Usage Considerations\n\n- **Skin Sensitivity** : While generally considered safe for most, some users may experience a **skin rash** ; it is advisable to patch test first.\n- **Medical Warnings** : Individuals with **auto-immune diseases** (like lupus or MS) or **bleeding conditions** should consult a doctor before use, as Lion\u0027s Mane may stimulate the immune system or slow blood clotting.\n- **Exfoliation Method** : When using on the face, use gentle, circular motions to avoid micro-tears, especially with salt-based abrasives.[[1]](https://www.webmd.com/vitamins/ai/ingredientmono-1536/lions-mane-mushroom#:~:text=When%20taken%20by%20mouth:%20Lion\u0027s,symptoms%20of%20auto-immune%20diseases.)[[2]](https://www.mskcc.org/cancer-care/integrative-medicine/herbs/lions-mane-mushroom#:~:text=What%20is%20it?,Skin%20rash)[[3]](https://www.instagram.com/p/DVMTWhEDlSg/#:~:text=%E2%9C%A8%20Salon%20Range%20Creamy%20Face,NaturalSkincare%20%23SelfCareRituals%20%23GlowNaturally%20%23SandalwoodAndChamomile)[[4]](https://www.midwestseasaltcompany.com/exfoliating-lions-main-mushroom-scrub-128oz/#:~:text=Product%20Description,Choose%20Options)\n\nAre you looking for a **specific skin concern** like anti-aging or acne, or do you need help finding a **travel-sized** option?","items":[{"type":"ai_overview_element","position":"left","title":null,"text":"Lion\u0027s mane salt scrubs are designed to exfoliate and nourish the skin by combining mineral-rich salts with the antioxidant and anti-inflammatory benefits of Lion\u0027s Mane mushroom extract. These scrubs are primarily used to improve skin texture, support collagen production, and provide deep hydration. Saltability \u002B3","markdown":"Lion\u0027s mane salt scrubs are designed to exfoliate and nourish the skin by combining mineral-rich salts with the antioxidant and anti-inflammatory benefits of **Lion\u0027s Mane mushroom extract** . These scrubs are primarily used to improve skin texture, support collagen production, and provide deep hydration.[[1]](https://www.saltability.com/products/himalayan-salt-lions-mane-scrub-8-oz?srsltid=AfmBOopE2O0bHE_871-01kdbqIzK25yA2ql5bS_p76j5zBzgE0d1tR_6#:~:text=$24.00%20USD,per%20week%20for%20best%20results.)[[2]](https://www.google.com/search?q=product\u0026prds=pvt:hg,productid:6627771179973779464,catalogid:8916746914933518999,gpcid:10023773780186035872\u0026ibp=oshop)[[3]](https://moonandskin.com/blogs/glow-up/discovering-the-lions-mane-mushroom-benefits-for-skin-natures-hidden-gem?srsltid=AfmBOoqvjhD1TuIZ5st90HEseVct4URyfCmZwyj7k35j9odeJPLJv-YT#:~:text=By%20incorporating%20lion\u0027s%20mane%20into%20our%20skincare%20regimen%2C%20we%20can,the%20effects%20of%20sun%20exposure.)[[4]](https://skintherapy.com/from-the-forest-to-your-face-how-mushrooms-are-revolutionizing-skincare/#:~:text=Lion\u0027s%20Mane:%20This%20mushroom%20contains,to%20help%20support%20healthy%20skin.)","links":null,"images":null,"references":[{"type":"ai_overview_reference","position":"left","source":"Saltability","domain":"www.saltability.com","url":"https://www.saltability.com/products/himalayan-salt-lions-mane-scrub-8-oz?srsltid=AfmBOopE2O0bHE_871-01kdbqIzK25yA2ql5bS_p76j5zBzgE0d1tR_6#:~:text=$24.00%20USD,per%20week%20for%20best%20results.","title":"Himalayan Salt Lion\u0027s Mane Scrub (8 oz) - Saltability","text":"Himalayan Salt Lion\u0027s Mane Scrub (8 oz) ... Shipping calculated at checkout. ... Refresh and renew your skin with our Himalayan Sa..."},{"type":"ai_overview_reference","position":"left","source":"Google","domain":"www.google.com","url":"https://www.google.com/search?q=product\u0026prds=pvt:hg,productid:6627771179973779464,catalogid:8916746914933518999,gpcid:10023773780186035872\u0026ibp=oshop","title":"Himalayan Salt Lion\u0027s Mane Scrub","text":"Refresh and renew your skin with our Himalayan Salt Lion\u2019s Mane Scrub, a mineral-rich exfoliating treatment designed to gently pol..."},{"type":"ai_overview_reference","position":"left","source":"Moon and Skin","domain":"moonandskin.com","url":"https://moonandskin.com/blogs/glow-up/discovering-the-lions-mane-mushroom-benefits-for-skin-natures-hidden-gem?srsltid=AfmBOoqvjhD1TuIZ5st90HEseVct4URyfCmZwyj7k35j9odeJPLJv-YT#:~:text=By%20incorporating%20lion\u0027s%20mane%20into%20our%20skincare%20regimen%2C%20we%20can,the%20effects%20of%20sun%20exposure.","title":"The Incredible Benefits of Lion\u0027s Mane Mushroom for Skin","text":"As clean beauty enthusiasts, we at Moon and Skin are dedicated to embracing nature\u0027s gifts and integrating them into our skincare ..."},{"type":"ai_overview_reference","position":"left","source":"Advanced Skin Therapeutics","domain":"skintherapy.com","url":"https://skintherapy.com/from-the-forest-to-your-face-how-mushrooms-are-revolutionizing-skincare/#:~:text=Lion\u0027s%20Mane:%20This%20mushroom%20contains,to%20help%20support%20healthy%20skin.","title":"From the Forest to Your Face - Advanced Skin Therapeutics","text":"From the Forest to Your Face: How Mushrooms are Revolutionizing Skincare. Mushrooms are not just for eating! These humble fungi ar..."}]},{"type":"ai_overview_element","position":"left","title":"Benefits for Face and Body","text":"Exfoliation and Renewal : Mineral-rich Sea, Himalayan, or Dead Sea salts gently polish away dead skin cells to reveal smoother, more radiant skin underneath. Anti-Aging Support : Lion\u0027s Mane mushroom contains polysaccharides and antioxidants that may boost collagen and elasticity, helping to reduce the appearance of fine lines. Soothing Inflammation : Its anti-inflammatory properties can help reduce redness, calm irritation, and support natural skin healing. Hydration : Formulations often include nourishing oils like sweet almond and jojoba oil, which lock in moisture and leave the skin feeling soft.","markdown":"- **Exfoliation and Renewal** : Mineral-rich Sea, Himalayan, or Dead Sea salts gently polish away dead skin cells to reveal smoother, more radiant skin underneath.\n- **Anti-Aging Support** : Lion\u0027s Mane mushroom contains polysaccharides and antioxidants that may boost **collagen and elasticity** , helping to reduce the appearance of fine lines.\n- **Soothing Inflammation** : Its anti-inflammatory properties can help reduce redness, calm irritation, and support natural skin healing.\n- **Hydration** : Formulations often include nourishing oils like **sweet almond and jojoba oil** , which lock in moisture and leave the skin feeling soft.[[1]](https://www.saltability.com/products/himalayan-salt-lions-mane-scrub-8-oz?srsltid=AfmBOopE2O0bHE_871-01kdbqIzK25yA2ql5bS_p76j5zBzgE0d1tR_6#:~:text=$24.00%20USD,per%20week%20for%20best%20results.)[[2]](https://www.google.com/search?q=product\u0026prds=pvt:hg,productid:6627771179973779464,catalogid:8916746914933518999,gpcid:10023773780186035872\u0026ibp=oshop)[[3]](https://www.instagram.com/p/DVMTWhEDlSg/#:~:text=%E2%9C%A8%20BUY%204%2C%20GET%202,saltability)[[4]](https://eatfungies.com/blogs/news/perfect-your-skincare-routine-with-lion-s-mane?srsltid=AfmBOorDwjG0ATx5bAHrjak0vmm5O2XXeOEENFyGHgbpsxNgt9xVJJ2D#:~:text=Cheat%20Sheet,fight%20inflammation%20before%20it%20starts.)[[5]](https://skintherapy.com/from-the-forest-to-your-face-how-mushrooms-are-revolutionizing-skincare/#:~:text=Lion\u0027s%20Mane:%20This%20mushroom%20contains,to%20help%20support%20healthy%20skin.)[[6]](https://moonandskin.com/blogs/glow-up/discovering-the-lions-mane-mushroom-benefits-for-skin-natures-hidden-gem?srsltid=AfmBOoqvjhD1TuIZ5st90HEseVct4URyfCmZwyj7k35j9odeJPLJv-YT#:~:text=By%20incorporating%20lion\u0027s%20mane%20into%20our%20skincare%20regimen%2C%20we%20can,the%20effects%20of%20sun%20exposure.)","links":null,"images":null,"references":[{"type":"ai_overview_reference","position":"left","source":"Saltability","domain":"www.saltability.com","url":"https://www.saltability.com/products/himalayan-salt-lions-mane-scrub-8-oz?srsltid=AfmBOopE2O0bHE_871-01kdbqIzK25yA2ql5bS_p76j5zBzgE0d1tR_6#:~:text=$24.00%20USD,per%20week%20for%20best%20results.","title":"Himalayan Salt Lion\u0027s Mane Scrub (8 oz) - Saltability","text":"Himalayan Salt Lion\u0027s Mane Scrub (8 oz) ... Shipping calculated at checkout. ... Refresh and renew your skin with our Himalayan Sa..."},{"type":"ai_overview_reference","position":"left","source":"Google","domain":"www.google.com","url":"https://www.google.com/search?q=product\u0026prds=pvt:hg,productid:6627771179973779464,catalogid:8916746914933518999,gpcid:10023773780186035872\u0026ibp=oshop","title":"Himalayan Salt Lion\u0027s Mane Scrub","text":"Refresh and renew your skin with our Himalayan Salt Lion\u2019s Mane Scrub, a mineral-rich exfoliating treatment designed to gently pol..."},{"type":"ai_overview_reference","position":"left","source":"Instagram","domain":"www.instagram.com","url":"https://www.instagram.com/p/DVMTWhEDlSg/#:~:text=%E2%9C%A8%20BUY%204%2C%20GET%202,saltability","title":"BUY 4, GET 2 FREE Our Himalayan Salt Lion\u0027s Mane Scrub is ...","text":"\u2728 BUY 4, GET 2 FREE \u2728 Our Himalayan Salt Lion\u0027s Mane Scrub is on special, and this is the perfect time to stock up. Just add 6 scr..."},{"type":"ai_overview_reference","position":"left","source":"Fungies","domain":"eatfungies.com","url":"https://eatfungies.com/blogs/news/perfect-your-skincare-routine-with-lion-s-mane?srsltid=AfmBOorDwjG0ATx5bAHrjak0vmm5O2XXeOEENFyGHgbpsxNgt9xVJJ2D#:~:text=Cheat%20Sheet,fight%20inflammation%20before%20it%20starts.","title":"Perfect Your Skincare Routine with Lion\u0027s Mane - Fungies","text":"Cheat Sheet * Lion\u0027s Mane mushrooms contain polysaccharides, phenols, and flavonoids that benefit skin health. * Lion\u0027s Mane mushr..."},{"type":"ai_overview_reference","position":"left","source":"Advanced Skin Therapeutics","domain":"skintherapy.com","url":"https://skintherapy.com/from-the-forest-to-your-face-how-mushrooms-are-revolutionizing-skincare/#:~:text=Lion\u0027s%20Mane:%20This%20mushroom%20contains,to%20help%20support%20healthy%20skin.","title":"From the Forest to Your Face - Advanced Skin Therapeutics","text":"From the Forest to Your Face: How Mushrooms are Revolutionizing Skincare. Mushrooms are not just for eating! These humble fungi ar..."},{"type":"ai_overview_reference","position":"left","source":"Moon and Skin","domain":"moonandskin.com","url":"https://moonandskin.com/blogs/glow-up/discovering-the-lions-mane-mushroom-benefits-for-skin-natures-hidden-gem?srsltid=AfmBOoqvjhD1TuIZ5st90HEseVct4URyfCmZwyj7k35j9odeJPLJv-YT#:~:text=By%20incorporating%20lion\u0027s%20mane%20into%20our%20skincare%20regimen%2C%20we%20can,the%20effects%20of%20sun%20exposure.","title":"The Incredible Benefits of Lion\u0027s Mane Mushroom for Skin","text":"As clean beauty enthusiasts, we at Moon and Skin are dedicated to embracing nature\u0027s gifts and integrating them into our skincare ..."}]},{"type":"ai_overview_element","position":"left","title":"Recommended Products","text":"The following products incorporate Lion\u0027s Mane mushroom into exfoliating salt-based formulas:","markdown":"The following products incorporate Lion\u0027s Mane mushroom into exfoliating salt-based formulas:[[1]](https://www.midwestseasaltcompany.com/exfoliating-lions-main-mushroom-scrub-128oz/)","links":null,"images":null,"references":[{"type":"ai_overview_reference","position":"left","source":"The Midwest Sea Salt Company","domain":"www.midwestseasaltcompany.com","url":"https://www.midwestseasaltcompany.com/exfoliating-lions-main-mushroom-scrub-128oz/","title":"Exfoliating Lions Main Mushroom Scrub - 128oz","text":"* Overview. Formulated to gently exfoliate while supporting skin balance, this scrub features Lion\u0027s Mane mushroom for a nourishin..."}]},{"type":"ai_overview_shopping","position":"left","title":null,"markdown":"[![Himalayan Salt Lion\u0026#39;s Mane Scrub](https://api.dataforseo.com/cdn/i/03161257-4353-0139-0000-f13017828fb5:1)\nHimalayan Salt Lion\u0027s Mane Scrub $24.00 Saltability](https://www.google.com/search?ibp=oshop\u0026prds=pvt:hg,pvo:29,imageDocid:14355365782867049316,gpcid:10023773780186035872,headlineOfferDocid:4724190994376421910,catalogid:8916746914933518999,productDocid:6627771179973779464\u0026q=product\u0026sa=X\u0026ved=2ahUKEwiiucGuoaSTAxX4mGoFHehCGZMQgLcPegQICBAC)","items":[{"type":"ai_overview_shopping_element","product_id":"8916746914933518999","title":"Himalayan Salt Lion\u0027s Mane Scrub","url":"https://www.google.com/search?ibp=oshop\u0026prds=pvt:hg,pvo:29,imageDocid:14355365782867049316,gpcid:10023773780186035872,headlineOfferDocid:4724190994376421910,catalogid:8916746914933518999,productDocid:6627771179973779464\u0026q=product\u0026sa=X\u0026ved=2ahUKEwiiucGuoaSTAxX4mGoFHehCGZMQgLcPegQICBAC","domain":"www.google.com","rating":null,"price":{"current":24,"regular":null,"max_value":null,"currency":"USD","is_price_range":false,"displayed_price":"$24.00"},"seller":"Saltability","snippet":null,"marketplace":null,"marketplace_url":null,"image_url":"https://api.dataforseo.com/cdn/i/03161257-4353-0139-0000-f13017828fb5:0"}]},{"type":"ai_overview_shopping","position":"left","title":null,"markdown":"[![Exfoliating Lions Main Mushroom Scrub](https://api.dataforseo.com/cdn/i/03161257-4353-0139-0000-f13017828fb5:3)\nExfoliating Lions Main Mushroom Scrub $57.03 Walmart - The Midwest Sea Salt Company \u0026 more](https://www.google.com/search?ibp=oshop\u0026prds=pvt:hg,pvo:29,mid:576462878899398168,imageDocid:6383926006675907478,headlineOfferDocid:15373118500153604702,catalogid:4621011338833908465,productDocid:298150119403178508\u0026q=product\u0026sa=X\u0026ved=2ahUKEwiiucGuoaSTAxX4mGoFHehCGZMQgLcPegQICBAQ)","items":[{"type":"ai_overview_shopping_element","product_id":"4621011338833908465","title":"Exfoliating Lions Main Mushroom Scrub","url":"https://www.google.com/search?ibp=oshop\u0026prds=pvt:hg,pvo:29,mid:576462878899398168,imageDocid:6383926006675907478,headlineOfferDocid:15373118500153604702,catalogid:4621011338833908465,productDocid:298150119403178508\u0026q=product\u0026sa=X\u0026ved=2ahUKEwiiucGuoaSTAxX4mGoFHehCGZMQgLcPegQICBAQ","domain":"www.google.com","rating":null,"price":{"current":57.03,"regular":null,"max_value":null,"currency":"USD","is_price_range":false,"displayed_price":"$57.03"},"seller":"Walmart - The Midwest Sea Salt Company","snippet":null,"marketplace":null,"marketplace_url":null,"image_url":"https://api.dataforseo.com/cdn/i/03161257-4353-0139-0000-f13017828fb5:2"}]},{"type":"ai_overview_element","position":"left","title":"Safety and Usage Considerations","text":"Skin Sensitivity : While generally considered safe for most, some users may experience a skin rash ; it is advisable to patch test first. Medical Warnings : Individuals with auto-immune diseases (like lupus or MS) or bleeding conditions should consult a doctor before use, as Lion\u0027s Mane may stimulate the immune system or slow blood clotting. Exfoliation Method : When using on the face, use gentle, circular motions to avoid micro-tears, especially with salt-based abrasives.","markdown":"- **Skin Sensitivity** : While generally considered safe for most, some users may experience a **skin rash** ; it is advisable to patch test first.\n- **Medical Warnings** : Individuals with **auto-immune diseases** (like lupus or MS) or **bleeding conditions** should consult a doctor before use, as Lion\u0027s Mane may stimulate the immune system or slow blood clotting.\n- **Exfoliation Method** : When using on the face, use gentle, circular motions to avoid micro-tears, especially with salt-based abrasives.[[1]](https://www.webmd.com/vitamins/ai/ingredientmono-1536/lions-mane-mushroom#:~:text=When%20taken%20by%20mouth:%20Lion\u0027s,symptoms%20of%20auto-immune%20diseases.)[[2]](https://www.mskcc.org/cancer-care/integrative-medicine/herbs/lions-mane-mushroom#:~:text=What%20is%20it?,Skin%20rash)[[3]](https://www.instagram.com/p/DVMTWhEDlSg/#:~:text=%E2%9C%A8%20Salon%20Range%20Creamy%20Face,NaturalSkincare%20%23SelfCareRituals%20%23GlowNaturally%20%23SandalwoodAndChamomile)[[4]](https://www.midwestseasaltcompany.com/exfoliating-lions-main-mushroom-scrub-128oz/#:~:text=Product%20Description,Choose%20Options)","links":null,"images":null,"references":[{"type":"ai_overview_reference","position":"left","source":"WebMD","domain":"www.webmd.com","url":"https://www.webmd.com/vitamins/ai/ingredientmono-1536/lions-mane-mushroom#:~:text=When%20taken%20by%20mouth:%20Lion\u0027s,symptoms%20of%20auto-immune%20diseases.","title":"Lion\u0027s Mane Mushroom - Uses, Side Effects, and More - WebMD","text":"Side Effects. When taken by mouth: Lion\u0027s mane mushroom is possibly safe when used in a dose of 1 gram daily for 16 weeks. Side ef..."},{"type":"ai_overview_reference","position":"left","source":"Memorial Sloan Kettering Cancer Center","domain":"www.mskcc.org","url":"https://www.mskcc.org/cancer-care/integrative-medicine/herbs/lions-mane-mushroom#:~:text=What%20is%20it?,Skin%20rash","title":"Lion\u0027s Mane Mushroom | Memorial Sloan Kettering Cancer ...","text":"What is it? Lion\u0027s mane mushroom is used in East Asian medical systems to improve general health. It also comes as dietary supplem..."},{"type":"ai_overview_reference","position":"left","source":"Instagram","domain":"www.instagram.com","url":"https://www.instagram.com/p/DVMTWhEDlSg/#:~:text=%E2%9C%A8%20Salon%20Range%20Creamy%20Face,NaturalSkincare%20%23SelfCareRituals%20%23GlowNaturally%20%23SandalwoodAndChamomile","title":"\u2728 BUY 4, GET 2 FREE \u2728 Our Himalayan Salt Lion\u2019s Mane Scrub is ...","text":"\u2728 Salon Range Creamy Face Scrub. I love this gentle, creamy scrub. It\u0027s like a mini facial at home. Infused with soothing chamomil..."},{"type":"ai_overview_reference","position":"left","source":"The Midwest Sea Salt Company","domain":"www.midwestseasaltcompany.com","url":"https://www.midwestseasaltcompany.com/exfoliating-lions-main-mushroom-scrub-128oz/#:~:text=Product%20Description,Choose%20Options","title":"Exfoliating Lions Main Mushroom Scrub - 128oz","text":"* Product Description. Overview. Formulated to gently exfoliate while supporting skin balance, this scrub features Lion\u0027s Mane mus..."}]},{"type":"ai_overview_element","position":"left","title":"specific skin concern travel-sized","text":null,"markdown":"Are you looking for a **specific skin concern** like anti-aging or acne, or do you need help finding a **travel-sized** option?","links":null,"images":null,"references":null}],"references":[{"type":"ai_overview_reference","position":"right","source":"Google","domain":"www.google.com","url":"https://www.google.com/search?q=product\u0026prds=pvt:hg,productid:6627771179973779464,catalogid:8916746914933518999,gpcid:10023773780186035872\u0026ibp=oshop","title":"Himalayan Salt Lion\u0027s Mane Scrub","text":"Refresh and renew your skin with our Himalayan Salt Lion\u2019s Mane Scrub, a mineral-rich exfoliating treatment designed to gently pol..."},{"type":"ai_overview_reference","position":"right","source":"Instagram","domain":"www.instagram.com","url":"https://www.instagram.com/p/DVMTWhEDlSg/#:~:text=%E2%9C%A8%20BUY%204%2C%20GET%202,saltability","title":"BUY 4, GET 2 FREE Our Himalayan Salt Lion\u0027s Mane Scrub is ...","text":"\u2728 BUY 4, GET 2 FREE \u2728 Our Himalayan Salt Lion\u0027s Mane Scrub is on special, and this is the perfect time to stock up. Just add 6 scr..."},{"type":"ai_overview_reference","position":"right","source":"Instagram","domain":"www.instagram.com","url":"https://www.instagram.com/p/DVMTWhEDlSg/#:~:text=%E2%9C%A8%20Salon%20Range%20Creamy%20Face,NaturalSkincare%20%23SelfCareRituals%20%23GlowNaturally%20%23SandalwoodAndChamomile","title":"\u2728 BUY 4, GET 2 FREE \u2728 Our Himalayan Salt Lion\u2019s Mane Scrub is ...","text":"\u2728 Salon Range Creamy Face Scrub. I love this gentle, creamy scrub. It\u0027s like a mini facial at home. Infused with soothing chamomil..."},{"type":"ai_overview_reference","position":"right","source":"Moon and Skin","domain":"moonandskin.com","url":"https://moonandskin.com/blogs/glow-up/discovering-the-lions-mane-mushroom-benefits-for-skin-natures-hidden-gem?srsltid=AfmBOoqvjhD1TuIZ5st90HEseVct4URyfCmZwyj7k35j9odeJPLJv-YT#:~:text=By%20incorporating%20lion\u0027s%20mane%20into%20our%20skincare%20regimen%2C%20we%20can,the%20effects%20of%20sun%20exposure.","title":"The Incredible Benefits of Lion\u0027s Mane Mushroom for Skin","text":"As clean beauty enthusiasts, we at Moon and Skin are dedicated to embracing nature\u0027s gifts and integrating them into our skincare ..."},{"type":"ai_overview_reference","position":"right","source":"The Midwest Sea Salt Company","domain":"www.midwestseasaltcompany.com","url":"https://www.midwestseasaltcompany.com/exfoliating-lions-main-mushroom-scrub-128oz/#:~:text=Product%20Description,Choose%20Options","title":"Exfoliating Lions Main Mushroom Scrub - 128oz","text":"* Product Description. Overview. Formulated to gently exfoliate while supporting skin balance, this scrub features Lion\u0027s Mane mus..."},{"type":"ai_overview_reference","position":"right","source":"WebMD","domain":"www.webmd.com","url":"https://www.webmd.com/vitamins/ai/ingredientmono-1536/lions-mane-mushroom#:~:text=When%20taken%20by%20mouth:%20Lion\u0027s,symptoms%20of%20auto-immune%20diseases.","title":"Lion\u0027s Mane Mushroom - Uses, Side Effects, and More - WebMD","text":"Side Effects. When taken by mouth: Lion\u0027s mane mushroom is possibly safe when used in a dose of 1 gram daily for 16 weeks. Side ef..."},{"type":"ai_overview_reference","position":"right","source":"Memorial Sloan Kettering Cancer Center","domain":"www.mskcc.org","url":"https://www.mskcc.org/cancer-care/integrative-medicine/herbs/lions-mane-mushroom#:~:text=What%20is%20it?,Skin%20rash","title":"Lion\u0027s Mane Mushroom | Memorial Sloan Kettering Cancer ...","text":"What is it? Lion\u0027s mane mushroom is used in East Asian medical systems to improve general health. It also comes as dietary supplem..."},{"type":"ai_overview_reference","position":"right","source":"Fungies","domain":"eatfungies.com","url":"https://eatfungies.com/blogs/news/perfect-your-skincare-routine-with-lion-s-mane?srsltid=AfmBOorDwjG0ATx5bAHrjak0vmm5O2XXeOEENFyGHgbpsxNgt9xVJJ2D#:~:text=Cheat%20Sheet,fight%20inflammation%20before%20it%20starts.","title":"Perfect Your Skincare Routine with Lion\u0027s Mane - Fungies","text":"Cheat Sheet * Lion\u0027s Mane mushrooms contain polysaccharides, phenols, and flavonoids that benefit skin health. * Lion\u0027s Mane mushr..."},{"type":"ai_overview_reference","position":"right","source":"Google","domain":"www.google.com","url":"https://www.google.com/search?q=product\u0026prds=pvt:hg,productid:298150119403178508,catalogid:4621011338833908465,mid:576462878899398168\u0026ibp=oshop","title":"Exfoliating Lions Main Mushroom Scrub","text":"Overview Formulated to gently exfoliate while supporting skin balance, this scrub features Lion\u0027s Mane mushroom for a nourishing t..."},{"type":"ai_overview_reference","position":"right","source":"Google","domain":"www.google.com","url":"https://www.google.com/search?q=product\u0026prds=pvt:hg,productid:7297618303635761298,catalogid:9786592570481028313\u0026ibp=oshop","title":"Exfoliating Lions Main Mushroom Scrub","text":"Overview Formulated to gently exfoliate while supporting skin balance, this scrub features Lion\u0027s Mane mushroom for a nourishing t..."},{"type":"ai_overview_reference","position":"right","source":"Google","domain":"www.google.com","url":"https://www.google.com/search?q=product\u0026prds=pvt:hg,productid:11995534751749398251,catalogid:7286353642936147147,gpcid:4756473384681669255,mid:576462878899398168\u0026ibp=oshop","title":"Exfoliating Lions Main Mushroom Scrub","text":"Overview Formulated to gently exfoliate while supporting skin balance, this scrub features Lion\u0027s Mane mushroom for a nourishing t..."},{"type":"ai_overview_reference","position":"right","source":"Google","domain":"www.google.com","url":"https://www.google.com/search?q=product\u0026prds=pvt:hg,productid:8000089833852050309,catalogid:8960174552859667425\u0026ibp=oshop","title":"Exfoliating Lions Main Mushroom Scrub","text":"Overview Formulated to gently exfoliate while supporting skin balance, this scrub features Lion\u0027s Mane mushroom for a nourishing t..."},{"type":"ai_overview_reference","position":"right","source":"Saltability","domain":"www.saltability.com","url":"https://www.saltability.com/products/himalayan-salt-lions-mane-scrub-8-oz?srsltid=AfmBOopE2O0bHE_871-01kdbqIzK25yA2ql5bS_p76j5zBzgE0d1tR_6#:~:text=$24.00%20USD,per%20week%20for%20best%20results.","title":"Himalayan Salt Lion\u0027s Mane Scrub (8 oz) - Saltability","text":"Himalayan Salt Lion\u0027s Mane Scrub (8 oz) ... Shipping calculated at checkout. ... Refresh and renew your skin with our Himalayan Sa..."},{"type":"ai_overview_reference","position":"right","source":"Advanced Skin Therapeutics","domain":"skintherapy.com","url":"https://skintherapy.com/from-the-forest-to-your-face-how-mushrooms-are-revolutionizing-skincare/#:~:text=Lion\u0027s%20Mane:%20This%20mushroom%20contains,to%20help%20support%20healthy%20skin.","title":"From the Forest to Your Face - Advanced Skin Therapeutics","text":"From the Forest to Your Face: How Mushrooms are Revolutionizing Skincare. Mushrooms are not just for eating! These humble fungi ar..."}],"rectangle":null}]}]}]}